cortexapps_cli/cli.py
cortexapps_cli/command_options.py
cortexapps_cli/commands/api_keys.py
cortexapps_cli/commands/audit_logs.py
cortexapps_cli/commands/backup.py
cortexapps_cli/commands/backup_commands/cortex_export.py
cortexapps_cli/commands/catalog.py
cortexapps_cli/commands/custom_data.py
cortexapps_cli/commands/custom_events.py
cortexapps_cli/commands/custom_metrics.py
cortexapps_cli/commands/dependencies.py
cortexapps_cli/commands/deploys.py
cortexapps_cli/commands/discovery_audit.py
cortexapps_cli/commands/docs.py
cortexapps_cli/commands/entity_relationship_types.py
cortexapps_cli/commands/entity_relationships.py
cortexapps_cli/commands/entity_types.py
cortexapps_cli/commands/gitops_logs.py
cortexapps_cli/commands/groups.py
cortexapps_cli/commands/initiatives.py
cortexapps_cli/commands/integrations.py
cortexapps_cli/commands/integrations_commands/aws.py
cortexapps_cli/commands/integrations_commands/azure_devops.py
cortexapps_cli/commands/integrations_commands/azure_resources.py
cortexapps_cli/commands/integrations_commands/circleci.py
cortexapps_cli/commands/integrations_commands/coralogix.py
cortexapps_cli/commands/integrations_commands/datadog.py
cortexapps_cli/commands/integrations_commands/github.py
cortexapps_cli/commands/integrations_commands/gitlab.py
cortexapps_cli/commands/integrations_commands/incidentio.py
cortexapps_cli/commands/integrations_commands/launchdarkly.py
cortexapps_cli/commands/integrations_commands/newrelic.py
cortexapps_cli/commands/integrations_commands/pagerduty.py
cortexapps_cli/commands/integrations_commands/prometheus.py
cortexapps_cli/commands/integrations_commands/sonarqube.py
cortexapps_cli/commands/ip_allowlist.py
cortexapps_cli/commands/on_call.py
cortexapps_cli/commands/packages.py
cortexapps_cli/commands/packages_commands/go.py
cortexapps_cli/commands/packages_commands/java.py
cortexapps_cli/commands/packages_commands/node.py
cortexapps_cli/commands/packages_commands/nuget.py
cortexapps_cli-1.10.0.dist-info/METADATA
cortexapps_cli-1.10.0.dist-info/WHEEL
cortexapps_cli-1.10.0.dist-info/entry_points.txt
cortexapps_cli-1.10.0.dist-info/licenses/LICENSE
cortexapps_cli-1.10.0.dist-info/RECORD
