Metadata-Version: 2.4
Name: cortexapps-cli
Version: 1.10.0
Summary: Command Line Interface for cortexapps
License: MIT
License-File: LICENSE
Author: Cortex Apps
Author-email: cortexapps@cortex.io
Requires-Python: >=3.11,<4.0
Classifier: License :: OSI Approved :: MIT License
Classifier: Operating System :: OS Independent
Classifier: Programming Language :: Python :: 3
Classifier: Programming Language :: Python :: 3.11
Classifier: Programming Language :: Python :: 3.12
Classifier: Programming Language :: Python :: 3.13
Classifier: Programming Language :: Python :: 3.14
Requires-Dist: click (<8.2)
Requires-Dist: pyyaml (>=6.0.1,<7)
Requires-Dist: requests (>=2.32.4,<3.0.0)
Requires-Dist: typer (>=0.12.5,<0.13.0)
Requires-Dist: urllib3 (>=2.6.0)
Project-URL: Bug Tracker, https://github.com/cortexapps/cli/issues
Project-URL: Changes,  https://github.com/cortexapps/cli/blob/main/HISTORY.md
Project-URL: Documentation,  https://github.com/cortexapps/cli/blob/main/README.rst
Project-URL: Homepage, https://github.com/cortexapps/cli
